{
    "Data file content": {
        "entry_list": [
            {
                "accession": "http://purl.obolibrary.org/obo/MS_1000579",
                "name": "MS1 spectrum",
                "ref": "MS"
            },
            {
                "accession": "http://purl.obolibrary.org/obo/MS_1000580",
                "name": "MSn spectrum",
                "ref": "MS"
            }
        ]
    },
    "Native spectrum identifier format": {
        "accession": "http://purl.obolibrary.org/obo/MS_1000768",
        "name": "Thermo nativeID format",
        "ref": "MS"
    },
    "Raw data file format": {
        "accession": "http://purl.obolibrary.org/obo/MS_1000563",
        "name": "Thermo RAW file",
        "ref": "MS"
    },
    "Data file checksum type": {
        "accession": "http://purl.obolibrary.org/obo/MS_1000569",
        "name": "SHA-1",
        "ref": "MS",
        "value": "67dde01f0f2e3e412791b68120249f982735dfbb"
    },
    "Ion source": {
        "accession": "http://purl.obolibrary.org/obo/MS_1000073",
        "name": "electrospray ionization",
        "ref": "MS"
    },
    "Inlet type": {
        "accession": "http://purl.obolibrary.org/obo/MS_1000057",
        "name": "electrospray inlet",
        "ref": "MS"
    },
    "Mass analyzer": {
        "accession": "http://purl.obolibrary.org/obo/MS_1000083",
        "name": "radial ejection linear ion trap",
        "ref": "MS"
    },
    "Detector": {
        "accession": "http://purl.obolibrary.org/obo/MS_1000253",
        "name": "electron multiplier",
        "ref": "MS"
    },
    "Data Transformation Name": {
        "entry_list": [
            {
                "accession": "http://purl.obolibrary.org/obo/MS_1000544",
                "name": "Conversion to mzML",
                "ref": "MS"
            }
        ]
    },
    "Data Transformation software version": {
        "value": "3.0.4833"
    },
    "Data Transformation software": {
        "accession": "http://purl.obolibrary.org/obo/MS_1000615",
        "name": "ProteoWizard",
        "ref": "MS"
    },
    "Instrument": {
        "accession": "http://purl.obolibrary.org/obo/MS_1001742",
        "name": "LTQ Orbitrap Velos",
        "ref": "MS"
    },
    "Instrument manufacturer": {
        "accession": "http://purl.obolibrary.org/obo/MS_1000483",
        "name": "Thermo Fisher Scientific instrument model",
        "ref": "MS"
    },
    "Instrument serial number": {
        "value": "Slot 116"
    },
    "Instrument software version": {
        "value": "2.6.0"
    },
    "Instrument software": {
        "accession": "http://purl.obolibrary.org/obo/MS_1000532",
        "name": "Xcalibur",
        "ref": "MS"
    },
    "Scan polarity": {
        "name": "positive scan",
        "ref": "MS",
        "accession": "http://purl.obolibrary.org/obo/MS_1000130"
    },
    "Spectrum representation": {
        "accession": "http://purl.obolibrary.org/obo/MS_1000128",
        "name": "profile spectrum",
        "ref": "MS"
    },
    "Time range": {
        "value": "0.0068-14.0009",
        "unit": {
            "name": "minute",
            "accession": "http://purl.obolibrary.org/obo/UO_0000031",
            "ref": "UO"
        }
    },
    "Scan m/z range": {
        "value": "75-900",
        "unit": {
            "name": "m/z",
            "ref": "MS",
            "accession": "http://purl.obolibrary.org/obo/MS_1000040"
        }
    },
    "Number of scans": {
        "value": 2000
    },
    "Raw Spectral Data File": {
        "entry_list": [
            {
                "value": "20100917_01_TomQC.raw"
            }
        ]
    },
    "MS Assay Name": {
        "value": "20100917_01_TomQC"
    },
    "Derived Spectral Data File": {
        "entry_list": [
            {
                "value": "20100917_01_TomQC.mzML"
            }
        ]
    },
    "Sample Name": {
        "value": "20100917_01_TomQC"
    }
}